Metadata-Version: 2.1
Name: Adil-Boudida.AI
Version: 0.1
Summary: Professional in Python Framwork for Artificial Intelligence
Author: Adil Boudida
Classifier: Programming Language :: Python :: 3
Classifier: Operating System :: OS Independent
Classifier: License :: OSI Approved :: MIT License
License-File: license.txt
